{ "usCongressBioId" : "I000032", "familyName" : "Irvin", "givenName" : "Alexander", "honorificPrefix" : "Mr.", "unaccentedFamilyName" : "Irvin", "unaccentedGivenName" : "Alexander", "birthDate" : "1800-01-18", "birthCirca" : false, "deathDate" : "1874-03-20", "deathCirca" : false, "profileText" : "A Representative from Pennsylvania; born in Penns Valley, Center County, Pa., January 18, 1800; attended the public schools; moved to Curwensville in 1820 and to Clearfield, Pa., in 1826; engaged in mercantile and lumbering pursuits; treasurer of Clearfield County 1828-1830; member of the State senate in 1837 and 1838; prothonotary of the court of common pleas in 1842; clerk of the several courts; recorder of deeds and register of wills of Clearfield County 1842-1844; elected as a Whig to the Thirtieth Congress (March 4, 1847-March 3, 1849); was not a candidate for renomination; United States marshal for the western district of Pennsylvania from January 17 to September 3, 1850, when he resigned, being succeeded by his brother, William Irvin; delegate to the Republican National Convention in 1872; engaged in mercantile pursuits at Clearfield, Clearfield County, Pa., until his death on March 20, 1874; interment in the Reed addition to the Old Graveyard.", "relationship" : [], "jobPositions" : [{ "job" : { "name" : "Representative", "jobType" : "CongressMemberJob" }, "startDate" : "1847-03-04", "startCirca" : false, "congressAffiliation" : { "congress" : { "name" : "The 30th United States Congress", "congressNumber" : 30, "congressType" : "USCongress", "startDate" : "1847-12-06", "endDate" : "1849-03-03" }, "partyAffiliation" : [{ "party" : { "name" : "Whig" } }], "caucusAffiliation" : [{ "party" : { "name" : "Whig" } }], "represents" : { "regionType" : "DistrictRegion", "regionCode" : "PA" } } }], "creativeWork" : [], "researchRecord" : [{ "name" : "Letter, Alexander Irvin, February 19, 1835, 1 item.", "recordType" : ["Papers"], "description" : "Letter written by Alexander Irvin to Josiah M. Smith.", "recordLocation" : { "name" : "Bureau of Archives and History", "location" : { "addressLocality" : "Harrisburg", "addressRegion" : "PA" }, "parentRecordLocation" : { "name" : "Pennsylvania State Archives", "location" : { "addressLocality" : "Harrisburg", "addressRegion" : "PA" } } } }] }
