{ "usCongressBioId" : "M000642", "familyName" : "Mercer", "givenName" : "Charles", "middleName" : "Fenton", "honorificPrefix" : "Mr.", "unaccentedFamilyName" : "Mercer", "unaccentedGivenName" : "Charles", "unaccentedMiddleName" : "Fenton", "birthDate" : "1778-06-16", "birthCirca" : false, "deathDate" : "1858-05-04", "deathCirca" : false, "profileText" : "A Representative from Virginia; born in Fredericksburg, Va., June 16, 1778; was graduated from Princeton College in 1797; took a postgraduate course in the same college and received his degree in 1800; studied law; was admitted to the bar in 1802 and commenced practice in Aldie, Loudoun County, Va.; member of the State house of delegates 1810-1817; during the War of 1812 was appointed lieutenant colonel of a Virginia regiment and then major in command at Norfolk, Va.; inspector general in 1814; aide-de-camp to Governor Barbour and brigadier general in command of the Second Virginia Brigade; projector and first president of the Chesapeake &amp; Ohio Canal Co. 1828-1833; delegate to the State constitutional convention in 1829; elected as a Federalist to the Fifteenth through the Seventeenth Congresses; reelected to the Eighteenth Congress as a Crawford Republican; reelected to the Nineteenth and Twentieth Congresses as an Adams; reelected as an Anti-Jacksonian to the Twenty-First through the Twenty-fourth Congresses; reelected as a Whig to the Twenty-fifth through Twenty-sixth Congresses and served from March 4, 1817, to December 26, 1839, when he resigned; chairman, Committee on Roads and Canals (Twenty-second through Twenty-fifth Congresses); was one of the originators of the plan for establishing the Free State of Liberia; vice president of the Virginia Colonization Society in 1836; vice president of the National Society of Agriculture in 1842; died in Howard, near Alexandria, Va., May 4, 1858; interment in Union Cemetery, Leesburg, Loudoun County, Va.", "relationship" : [{ "relationshipType" : "cousin", "relatedTo" : { "usCongressBioId" : "G000077", "familyName" : "Garnett", "givenName" : "Robert", "middleName" : "Selden", "honorificPrefix" : "Mr.", "unaccentedFamilyName" : "Garnett", "unaccentedGivenName" : "Robert", "unaccentedMiddleName" : "Selden", "birthDate" : "1789-04-26", "birthCirca" : false, "deathDate" : "1840-08-15", "deathCirca" : false } }], "jobPositions" : [{ "job" : { "name" : "Representative", "jobType" : "CongressMemberJob" }, "startDate" : "1817-12-01", "startCirca" : false, "congressAffiliation" : { "congress" : { "name" : "The 15th United States Congress", "congressNumber" : 15, "congressType" : "USCongress", "startDate" : "1817-03-04", "endDate" : "1819-03-03" }, "partyAffiliation" : [{ "party" : { "name" : "Federalist" } }], "caucusAffiliation" : [{ "party" : { "name" : "Federalist" } }], "represents" : { "regionType" : "DistrictRegion", "regionCode" : "VA" } } }, { "job" : { "name" : "Representative", "jobType" : "CongressMemberJob" }, "startDate" : "1819-12-06", "startCirca" : false, "congressAffiliation" : { "congress" : { "name" : "The 16th United States Congress", "congressNumber" : 16, "congressType" : "USCongress", "startDate" : "1819-12-06", "endDate" : "1821-03-03" }, "partyAffiliation" : [{ "party" : { "name" : "Federalist" } }], "caucusAffiliation" : [{ "party" : { "name" : "Whig" } }], "represents" : { "regionType" : "DistrictRegion", "regionCode" : "VA" } } }, { "job" : { "name" : "Representative", "jobType" : "CongressMemberJob" }, "startDate" : "1821-12-03", "startCirca" : false, "congressAffiliation" : { "congress" : { "name" : "The 17th United States Congress", "congressNumber" : 17, "congressType" : "USCongress", "startDate" : "1821-12-03", "endDate" : "1823-03-03" }, "partyAffiliation" : [{ "party" : { "name" : "Federalist" } }], "caucusAffiliation" : [{ "party" : { "name" : "Whig" } }], "represents" : { "regionType" : "DistrictRegion", "regionCode" : "VA" } } }, { "job" : { "name" : "Representative", "jobType" : "CongressMemberJob" }, "startDate" : "1823-12-01", "startCirca" : false, "congressAffiliation" : { "congress" : { "name" : "The 18th United States Congress", "congressNumber" : 18, "congressType" : "USCongress", "startDate" : "1823-12-01", "endDate" : "1825-03-03" }, "partyAffiliation" : [{ "party" : { "name" : "Crawford Republicans" } }], "caucusAffiliation" : [{ "party" : { "name" : "Whig" } }], "represents" : { "regionType" : "DistrictRegion", "regionCode" : "VA" } } }, { "job" : { "name" : "Representative", "jobType" : "CongressMemberJob" }, "startDate" : "1825-12-05", "startCirca" : false, "congressAffiliation" : { "congress" : { "name" : "The 19th United States Congress", "congressNumber" : 19, "congressType" : "USCongress", "startDate" : "1825-03-04", "endDate" : "1827-03-03" }, "partyAffiliation" : [{ "party" : { "name" : "Adams" } }], "caucusAffiliation" : [{ "party" : { "name" : "Whig" } }], "represents" : { "regionType" : "DistrictRegion", "regionCode" : "VA" } } }, { "job" : { "name" : "Representative", "jobType" : "CongressMemberJob" }, "startDate" : "1827-12-03", "startCirca" : false, "congressAffiliation" : { "congress" : { "name" : "The 20th United States Congress", "congressNumber" : 20, "congressType" : "USCongress", "startDate" : "1827-12-03", "endDate" : "1829-03-03" }, "partyAffiliation" : [{ "party" : { "name" : "Adams" } }], "caucusAffiliation" : [{ "party" : { "name" : "Whig" } }], "represents" : { "regionType" : "DistrictRegion", "regionCode" : "VA" } } }, { "job" : { "name" : "Representative", "jobType" : "CongressMemberJob" }, "startDate" : "1829-12-07", "startCirca" : false, "congressAffiliation" : { "congress" : { "name" : "The 21st United States Congress", "congressNumber" : 21, "congressType" : "USCongress", "startDate" : "1829-03-04", "endDate" : "1831-03-03" }, "partyAffiliation" : [{ "party" : { "name" : "Anti-Jacksonian" } }], "caucusAffiliation" : [{ "party" : { "name" : "Whig" } }], "represents" : { "regionType" : "DistrictRegion", "regionCode" : "VA" } } }, { "job" : { "name" : "Representative", "jobType" : "CongressMemberJob" }, "startDate" : "1831-12-05", "startCirca" : false, "congressAffiliation" : { "congress" : { "name" : "The 22nd United States Congress", "congressNumber" : 22, "congressType" : "USCongress", "startDate" : "1831-12-05", "endDate" : "1833-03-02" }, "partyAffiliation" : [{ "party" : { "name" : "Anti-Jacksonian" } }], "caucusAffiliation" : [{ "party" : { "name" : "Whig" } }], "represents" : { "regionType" : "DistrictRegion", "regionCode" : "VA" } } }, { "job" : { "name" : "Representative", "jobType" : "CongressMemberJob" }, "startDate" : "1833-12-02", "startCirca" : false, "congressAffiliation" : { "congress" : { "name" : "The 23rd United States Congress", "congressNumber" : 23, "congressType" : "USCongress", "startDate" : "1833-12-02", "endDate" : "1835-03-03" }, "partyAffiliation" : [{ "party" : { "name" : "Anti-Jacksonian" } }], "caucusAffiliation" : [{ "party" : { "name" : "Whig" } }], "represents" : { "regionType" : "DistrictRegion", "regionCode" : "VA" } } }, { "job" : { "name" : "Representative", "jobType" : "CongressMemberJob" }, "startDate" : "1835-03-04", "startCirca" : false, "congressAffiliation" : { "congress" : { "name" : "The 24th United States Congress", "congressNumber" : 24, "congressType" : "USCongress", "startDate" : "1835-12-07", "endDate" : "1837-03-03" }, "partyAffiliation" : [{ "party" : { "name" : "Anti-Jacksonian" } }], "caucusAffiliation" : [{ "party" : { "name" : "Whig" } }], "represents" : { "regionType" : "DistrictRegion", "regionCode" : "VA" } } }, { "job" : { "name" : "Representative", "jobType" : "CongressMemberJob" }, "startDate" : "1837-03-04", "startCirca" : false, "congressAffiliation" : { "congress" : { "name" : "The 25th United States Congress", "congressNumber" : 25, "congressType" : "USCongress", "startDate" : "1837-03-04", "endDate" : "1839-03-03" }, "partyAffiliation" : [{ "party" : { "name" : "Whig" } }], "caucusAffiliation" : [{ "party" : { "name" : "Whig" } }], "represents" : { "regionType" : "DistrictRegion", "regionCode" : "VA" } } }, { "job" : { "name" : "Representative", "jobType" : "CongressMemberJob" }, "startDate" : "1839-03-04", "startCirca" : false, "endDate" : "1839-12-26", "endCirca" : false, "departureReason" : "Resigned", "congressAffiliation" : { "congress" : { "name" : "The 26th United States Congress", "congressNumber" : 26, "congressType" : "USCongress", "startDate" : "1839-12-02", "endDate" : "1841-03-03" }, "departureReason" : "Resigned", "partyAffiliation" : [{ "party" : { "name" : "Whig" } }], "caucusAffiliation" : [{ "party" : { "name" : "Whig" } }], "represents" : { "regionType" : "DistrictRegion", "regionCode" : "VA" }, "note" : [{ "type" : "Note", "noteType" : "FootNote", "content" : "Resigned December 26, 1839." }] } }], "creativeWork" : [{ "freeFormCitationText" : "Carey, Mathew. <i>Letters on the colonization society; and on its probable results; under the following heads: the origin of the society; increase of the coloured population; manumission of slaves in this country; declarations of legislatures, and other assembled bodies, in favour of the society; situation of the colonists at Monrovia, and other towns ... Addressed to the Hon. C. F. Mercer</i>. New York: Arno Press, 1968. Reprint, Philadelphia: Stereotyped by L. Johnson, 1832." }, { "freeFormCitationText" : "Carter, Robert Allen. \"Virginia Federalist in Dissent: A Life of Charles Fenton Mercer.\" Ph.D. diss., University of Virginia, 1988." }, { "freeFormCitationText" : "Egerton, Douglas Rogers. \"Charles Fenton Mercer and the Foundations of Modern American Conservatism.\" Ph.D. diss., Georgetown University, 1985." }, { "freeFormCitationText" : "Garnett, James Mercer. <i>Biographical Sketch of Hon. Charles Fenton Mercer.</i> Richmond, Va.: Privately printed by Whittet and Shepperson, 1911." }, { "freeFormCitationText" : "Mason, Armistead Thomson. <i>Controversy between Armistead Thompson Mason and Charles Fenton Mercer</i>. [Washington: N.p., 1818]." }, { "freeFormCitationText" : "Mercer, Charles Fenton. <i>A discourse on popular education; delivered in the church at Princeton, the evening before the annual commencement of the College of New Jersey, September 26, 1826</i>. Princeton: Princeton Press, Printed for the societies, by D. A. Borrenstein, 1826." }, { "freeFormCitationText" : "------. <i>The farewell address of the Hon. C.F. Mercer to his constituents</i>. [N.p., 1839]." }, { "freeFormCitationText" : "------. <i>Speech of Mr. C. F. Mercer, on the subject of the Chesapeake and Ohio Canal, delivered in the convention of delegates, held at the city of Washington, November 7, 1823</i>. Washington: Printed by Gales &amp; Seaton. 1823." }, { "freeFormCitationText" : "------. <i>The weakness and inefficiency of the government of the United States of North America; by a late American statesman</i>. Edited by a member of the Middle Temple. London: Houlston &amp; Wright, 1863." }, { "freeFormCitationText" : "Scott, John. <i>Judge Scott's reply to Mr. Mercer</i>. [Richmond: N.p., 1839]." }], "researchRecord" : [{ "name" : "1825. 1 letter.", "recordType" : ["Papers"], "recordLocation" : { "name" : "Manuscript Division", "location" : { "addressLocality" : "Washington", "addressRegion" : "DC" }, "parentRecordLocation" : { "name" : "Library of Congress", "location" : { "addressLocality" : "Washington", "addressRegion" : "DC" } } } }, { "name" : "1816-1832. 25 items.", "recordType" : ["Papers"], "recordLocation" : { "name" : "New-York Historical Society", "location" : { "addressLocality" : "New York", "addressRegion" : "NY" } } }, { "name" : "Letters in William H. Harrison papers.", "recordType" : ["Papers"], "recordLocation" : { "name" : "New-York Historical Society", "location" : { "addressLocality" : "New York", "addressRegion" : "NY" } } }, { "name" : "12 letters.", "recordType" : ["Papers"], "recordLocation" : { "name" : "Boston Public Library", "location" : { "addressLocality" : "Boston", "addressRegion" : "MA" } } }, { "name" : "2 official letters (February 7, 1824; February 3, 1827) in the DeWitt Clinton collection.", "recordType" : ["Papers"], "description" : "Finding aid in repository.", "recordLocation" : { "name" : "Rare Book and Manuscript Library", "location" : { "addressLocality" : "New York", "addressRegion" : "NY" }, "parentRecordLocation" : { "name" : "Columbia University", "location" : { "addressLocality" : "New York", "addressRegion" : "NY" } } } }, { "name" : "1816-1854. 39 items.", "recordType" : ["Papers"], "description" : "Includes a diary (1816) and a 10 page autobiography (ca. 1839).", "recordLocation" : { "name" : "New Jersey Historical Society", "location" : { "addressLocality" : "Newark", "addressRegion" : "NJ" } } }, { "name" : "Letters in Colonization Records, Secretary of State Record Group, the A.J. Houston collection, and the Washington D. Miller papers.", "recordType" : ["Papers"], "recordLocation" : { "name" : "Texas State Library", "location" : { "addressLocality" : "Austin", "addressRegion" : "TX" } } }, { "name" : "1804-1845. 17 items in Mercer family and other papers.", "recordType" : ["Papers"], "description" : "Personal and business papers and correspondence, some relating to University of Virginia and some with political content. Finding aids for some collections.", "recordLocation" : { "name" : "University of Virginia Library", "location" : { "addressLocality" : "Charlottesville", "addressRegion" : "VA" } } }, { "name" : "In Mercer family papers, 1656-1869. 569 items.", "recordType" : ["Papers"], "description" : "Collection analyzed by repository.", "recordLocation" : { "name" : "Virginia Historical Society", "location" : { "addressLocality" : "Richmond", "addressRegion" : "VA" } } }, { "name" : "Diary (1853-1858, 2 volumes) and an autobiographical sketch (22 pages).", "recordType" : ["Papers"], "description" : "Finding aid in repository.", "recordLocation" : { "name" : "Archives Branch", "location" : { "addressLocality" : "Richmond", "addressRegion" : "VA" }, "parentRecordLocation" : { "name" : "Virginia State Library and Archives", "location" : { "addressLocality" : "Richmond", "addressRegion" : "VA" } } } }] }
