{ "usCongressBioId" : "P000088", "familyName" : "Parsons", "givenName" : "Herbert", "honorificPrefix" : "Mr.", "unaccentedFamilyName" : "Parsons", "unaccentedGivenName" : "Herbert", "birthDate" : "1869-10-28", "birthCirca" : false, "deathDate" : "1925-09-16", "deathCirca" : false, "image" : [{ "caption" : "Collection of the U.S. House of Representatives" }], "profileText" : "A Representative from New York; born in New York City, October 28, 1869; attended private schools in New York City, St. Paul's School, Concord, N.H., Yale University, the University of Berlin, Harvard Law School, and was graduated from Yale University in 1890; was admitted to the bar in 1894 and commenced practice in New York City; member of the board of aldermen of New York City 1900-1904; elected as a Republican to the Fifty-ninth, Sixtieth, and Sixty-first Congresses (March 4, 1905-March 3, 1911); unsuccessful candidate for reelection in 1910 to the Sixty-second Congress; resumed the practice of law in New York City; delegate to all Republican New York State conventions 1904-1920; delegate to the Republican National Conventions in 1908, 1912, 1916, and 1920; served on the general staff of the American Expeditionary Forces during the First World War; died in Pittsfield, Mass., September 16, 1925; interment in Lenox Cemetery, Lenox, Mass.", "relationship" : [], "jobPositions" : [{ "job" : { "name" : "Representative", "jobType" : "CongressMemberJob" }, "startDate" : "1905-03-04", "startCirca" : false, "congressAffiliation" : { "congress" : { "name" : "The 59th United States Congress", "congressNumber" : 59, "congressType" : "USCongress", "startDate" : "1905-03-04", "endDate" : "1907-03-04" }, "partyAffiliation" : [{ "party" : { "name" : "Republican" } }], "caucusAffiliation" : [{ "party" : { "name" : "Republican" } }], "represents" : { "regionType" : "DistrictRegion", "regionCode" : "NY" } } }, { "job" : { "name" : "Representative", "jobType" : "CongressMemberJob" }, "startDate" : "1907-03-04", "startCirca" : false, "congressAffiliation" : { "congress" : { "name" : "The 60th United States Congress", "congressNumber" : 60, "congressType" : "USCongress", "startDate" : "1907-12-02", "endDate" : "1909-03-04" }, "partyAffiliation" : [{ "party" : { "name" : "Republican" } }], "caucusAffiliation" : [{ "party" : { "name" : "Republican" } }], "represents" : { "regionType" : "DistrictRegion", "regionCode" : "NY" } } }, { "job" : { "name" : "Representative", "jobType" : "CongressMemberJob" }, "startDate" : "1909-03-04", "startCirca" : false, "congressAffiliation" : { "congress" : { "name" : "The 61st United States Congress", "congressNumber" : 61, "congressType" : "USCongress", "startDate" : "1909-03-04", "endDate" : "1911-03-04" }, "partyAffiliation" : [{ "party" : { "name" : "Republican" } }], "caucusAffiliation" : [{ "party" : { "name" : "Republican" } }], "represents" : { "regionType" : "DistrictRegion", "regionCode" : "NY" } } }], "creativeWork" : [], "researchRecord" : [{ "name" : "1898-1925. ca. 14,700 items.", "recordType" : ["Papers"], "description" : "Correspondence received from well known contemporaries, chiefly on political and social matters.", "recordLocation" : { "name" : "Columbia University", "location" : { "addressLocality" : "New York", "addressRegion" : "NY" } } }, { "name" : "Correspondence in McIlvaine family papers, 1862-1931. ca. 325 items.", "recordType" : ["Papers"], "description" : "Unpublished index in library.", "recordLocation" : { "name" : "University of Iowa Libraries", "location" : { "addressLocality" : "Iowa City", "addressRegion" : "IA" } } }] }
