{ "usCongressBioId" : "S000868", "familyName" : "Sterling", "givenName" : "Ansel", "honorificPrefix" : "Mr.", "unaccentedFamilyName" : "Sterling", "unaccentedGivenName" : "Ansel", "birthDate" : "1782-02-03", "birthCirca" : false, "deathDate" : "1853-11-06", "deathCirca" : false, "profileText" : "A Representative from Connecticut; born in Lyme, New London County, Conn., February 3, 1782; attended the common schools; studied law; was admitted to the bar in 1805 and commenced practice in Salisbury, Conn.; moved to Sharon, Litchfield County, in 1808 and continued the practice of his profession; member of the State house of representatives in 1815, 1818-1821, 1825, 1826, 1829, and 1835-1837, and served as clerk of the house in the sessions of 1815 and 1818-1820; elected as a Republican to the Seventeenth Congress and reelected as an Adams-Clay Republican candidate to the Eighteenth Congress (March 4, 1821-March 3, 1825); resumed legal practice; chief justice of the court of common pleas of Litchfield County 1838-1840; died in Sharon, Conn., November 6, 1853; interment in Sharon Burying Ground.", "relationship" : [{ "relationshipType" : "brother", "relatedTo" : { "usCongressBioId" : "S000871", "familyName" : "Sterling", "givenName" : "Micah", "honorificPrefix" : "Mr.", "unaccentedFamilyName" : "Sterling", "unaccentedGivenName" : "Micah", "birthDate" : "1784-11-05", "birthCirca" : false, "deathDate" : "1844-04-11", "deathCirca" : false } }], "jobPositions" : [{ "job" : { "name" : "Representative", "jobType" : "CongressMemberJob" }, "startDate" : "1821-12-03", "startCirca" : false, "congressAffiliation" : { "congress" : { "name" : "The 17th United States Congress", "congressNumber" : 17, "congressType" : "USCongress", "startDate" : "1821-12-03", "endDate" : "1823-03-03" }, "partyAffiliation" : [{ "party" : { "name" : "Republican" } }], "caucusAffiliation" : [{ "party" : { "name" : "Republican" } }], "represents" : { "regionType" : "StateRegion", "regionCode" : "CT" } } }, { "job" : { "name" : "Representative", "jobType" : "CongressMemberJob" }, "startDate" : "1823-12-01", "startCirca" : false, "congressAffiliation" : { "congress" : { "name" : "The 18th United States Congress", "congressNumber" : 18, "congressType" : "USCongress", "startDate" : "1823-12-01", "endDate" : "1825-03-03" }, "partyAffiliation" : [{ "party" : { "name" : "Adams-Clay Republican" } }], "caucusAffiliation" : [{ "party" : { "name" : "Adams-Clay Republican" } }], "represents" : { "regionType" : "StateRegion", "regionCode" : "CT" } } }], "creativeWork" : [], "researchRecord" : [] }
