{ "usCongressBioId" : "H000795", "familyName" : "Horsey", "givenName" : "Outerbridge", "unaccentedFamilyName" : "Horsey", "unaccentedGivenName" : "Outerbridge", "birthDate" : "1777", "birthCirca" : false, "deathDate" : "1842", "deathCirca" : false, "profileText" : "A Senator from Delaware; born near Laurel, Sussex County, Del., March 5, 1777; received a liberal education; studied law; admitted to the bar in 1807 and commenced practice in Wilmington, Del.; member, State house of representatives 1800-1802; attorney general of Delaware 1806-1810; elected in 1810 as a Federalist to the United States Senate to fill the vacancy caused by the death of Samuel White; reelected in 1815 and served from January 12, 1810, to March 3, 1821; was not a candidate for reelection; chairman, Committee on the District of Columbia (Sixteenth Congress); retired to his wife's estate, 'Needwood,' near Petersville, Frederick County, Md., and died there June 9, 1842; interment in St. John's Cemetery, Frederick, Md.", "relationship" : [], "jobPositions" : [{ "job" : { "name" : "Senator", "jobType" : "CongressMemberJob" }, "congressAffiliation" : { "congress" : { "name" : "The 11th United States Congress", "congressNumber" : 11, "congressType" : "USCongress", "startDate" : "1809-03-04", "endDate" : "1811-03-03" }, "partyAffiliation" : [{ "party" : { "name" : "Federalist" } }], "caucusAffiliation" : [{ "party" : { "name" : "Federalist" } }], "represents" : { "regionType" : "StateRegion", "regionCode" : "DE" } }, "startCirca" : false, "startDate" : "1810-01-12" }, { "job" : { "name" : "Senator", "jobType" : "CongressMemberJob" }, "congressAffiliation" : { "congress" : { "name" : "The 12th United States Congress", "congressNumber" : 12, "congressType" : "USCongress", "startDate" : "1811-11-04", "endDate" : "1813-03-03" }, "partyAffiliation" : [{ "party" : { "name" : "Federalist" } }], "caucusAffiliation" : [{ "party" : { "name" : "Federalist" } }], "represents" : { "regionType" : "StateRegion", "regionCode" : "DE" } } }, { "job" : { "name" : "Senator", "jobType" : "CongressMemberJob" }, "congressAffiliation" : { "congress" : { "name" : "The 13th United States Congress", "congressNumber" : 13, "congressType" : "USCongress", "startDate" : "1813-05-24", "endDate" : "1815-03-03" }, "partyAffiliation" : [{ "party" : { "name" : "Federalist" } }], "caucusAffiliation" : [{ "party" : { "name" : "Federalist" } }], "represents" : { "regionType" : "StateRegion", "regionCode" : "DE" } } }, { "job" : { "name" : "Senator", "jobType" : "CongressMemberJob" }, "congressAffiliation" : { "congress" : { "name" : "The 14th United States Congress", "congressNumber" : 14, "congressType" : "USCongress", "startDate" : "1815-12-04", "endDate" : "1817-03-03" }, "partyAffiliation" : [{ "party" : { "name" : "Federalist" } }], "caucusAffiliation" : [{ "party" : { "name" : "Federalist" } }], "represents" : { "regionType" : "StateRegion", "regionCode" : "DE" } } }, { "job" : { "name" : "Senator", "jobType" : "CongressMemberJob" }, "congressAffiliation" : { "congress" : { "name" : "The 15th United States Congress", "congressNumber" : 15, "congressType" : "USCongress", "startDate" : "1817-03-04", "endDate" : "1819-03-03" }, "partyAffiliation" : [{ "party" : { "name" : "Federalist" } }], "caucusAffiliation" : [{ "party" : { "name" : "Federalist" } }], "represents" : { "regionType" : "StateRegion", "regionCode" : "DE" } } }, { "job" : { "name" : "Senator", "jobType" : "CongressMemberJob" }, "congressAffiliation" : { "congress" : { "name" : "The 16th United States Congress", "congressNumber" : 16, "congressType" : "USCongress", "startDate" : "1819-12-06", "endDate" : "1821-03-03" }, "partyAffiliation" : [{ "party" : { "name" : "Federalist" } }], "caucusAffiliation" : [{ "party" : { "name" : "Federalist" } }], "represents" : { "regionType" : "StateRegion", "regionCode" : "DE" } } }], "creativeWork" : [], "researchRecord" : [{ "name" : "Items in various collections.", "recordType" : ["Papers"], "recordLocation" : { "name" : "Hagley Museum and Library", "location" : { "addressLocality" : "Greenville", "addressRegion" : "DE" } } }, { "name" : "Correspondence in various families of Leesburg, Virginia, papers, 1650-1961. Finding aid.", "recordType" : ["Papers"], "recordLocation" : { "name" : "Alderman Library", "location" : { "addressLocality" : "Charlottesville", "addressRegion" : "VA" }, "parentRecordLocation" : { "name" : "University of Virginia", "location" : { "addressLocality" : "Charlottesville", "addressRegion" : "VA" } } } }, { "name" : "1800-1821. 40 items.", "recordType" : ["Papers"], "recordLocation" : { "name" : "Historical Society of Delaware", "location" : { "addressLocality" : "Wilmington", "addressRegion" : "DE" } } }] }
