{ "usCongressBioId" : "H000079", "familyName" : "Hall", "givenName" : "William", "middleName" : "Augustus", "honorificPrefix" : "Mr.", "unaccentedFamilyName" : "Hall", "unaccentedGivenName" : "William", "unaccentedMiddleName" : "Augustus", "birthDate" : "1815-10-15", "birthCirca" : false, "deathDate" : "1888-12-15", "deathCirca" : false, "profileText" : "A Representative from Missouri; born in Portland, Maine, October 15, 1815; moved with his parents to Harpers Ferry, Va.; attended the public schools and Yale College; accompanied his father to Randolph County, Mo., in 1840; studied law; was admitted to the bar in 1841 and commenced practice in Huntsville, Mo.; moved to Fayette, Mo., and continued the practice of law; judge of the circuit court 1847-1861; during the Mexican War served as captain; delegate to the State constitutional convention in 1861; elected as a Democrat to the Thirty-seventh Congress to fill the vacancy caused by the expulsion of John B. Clark; reelected as a Unionist to the Thirty-eighth Congress and served from January 20, 1862, to March 3, 1865; was not a candidate for renomination in 1864; delegate to the Democratic National Convention in 1864; resumed the practice of law and also engaged in agricultural pursuits; died near Darkville, Randolph County, Mo., December 15, 1888; interment in the family private cemetery.", "relationship" : [{ "relationshipType" : "father", "relatedTo" : { "usCongressBioId" : "H000075", "familyName" : "Hall", "givenName" : "Uriel", "middleName" : "Sebree", "honorificPrefix" : "Mr.", "unaccentedFamilyName" : "Hall", "unaccentedGivenName" : "Uriel", "unaccentedMiddleName" : "Sebree", "birthDate" : "1852-04-12", "birthCirca" : false, "deathDate" : "1932-12-30", "deathCirca" : false } }, { "relationshipType" : "brother", "relatedTo" : { "usCongressBioId" : "H000077", "familyName" : "Hall", "givenName" : "Willard", "middleName" : "Preble", "honorificPrefix" : "Mr.", "unaccentedFamilyName" : "Hall", "unaccentedGivenName" : "Willard", "unaccentedMiddleName" : "Preble", "birthDate" : "1820-05-09", "birthCirca" : false, "deathDate" : "1882-11-03", "deathCirca" : false } }], "jobPositions" : [{ "job" : { "name" : "Representative", "jobType" : "CongressMemberJob" }, "startDate" : "1862-01-20", "startCirca" : false, "congressAffiliation" : { "congress" : { "name" : "The 37th United States Congress", "congressNumber" : 37, "congressType" : "USCongress", "startDate" : "1861-03-04", "endDate" : "1863-03-03" }, "partyAffiliation" : [{ "party" : { "name" : "Democrat" } }], "caucusAffiliation" : [{ "party" : { "name" : "Democrat" } }], "represents" : { "regionType" : "DistrictRegion", "regionCode" : "MO" }, "note" : [{ "type" : "Note", "noteType" : "FootNote", "content" : "Elected to fill vacancy caused by expulsion of John B. Clark, and took his seat January 20, 1862." }] } }, { "job" : { "name" : "Representative", "jobType" : "CongressMemberJob" }, "startDate" : "1863-03-04", "startCirca" : false, "congressAffiliation" : { "congress" : { "name" : "The 38th United States Congress", "congressNumber" : 38, "congressType" : "USCongress", "startDate" : "1863-03-04", "endDate" : "1865-03-04" }, "partyAffiliation" : [{ "party" : { "name" : "Unionist" } }], "caucusAffiliation" : [{ "party" : { "name" : "Unionist" } }], "represents" : { "regionType" : "DistrictRegion", "regionCode" : "MO" } } }], "creativeWork" : [], "researchRecord" : [] }
