{ "usCongressBioId" : "K000282", "familyName" : "Knickerbocker", "givenName" : "Herman", "honorificPrefix" : "Mr.", "unaccentedFamilyName" : "Knickerbocker", "unaccentedGivenName" : "Herman", "birthDate" : "1779-07-27", "birthCirca" : false, "deathDate" : "1855-01-30", "deathCirca" : false, "profileText" : "A Representative from New York; born in Albany, N.Y., July 27, 1779; completed preparatory studies; studied law; was admitted to the bar in 1803 and commenced practice in Albany, N.Y.; moved to Schaghticoke, near Albany, and became known as ``the Prince of Schaghticoke'' on account of his hospitality and liberality; elected as a Federalist to the Eleventh Congress (March 4, 1809-March 3, 1811); was not a candidate for reelection in 1810; served in the State assembly in 1816; judge of Rensselaer County; died in Williamsburg (now a part of New York City), N.Y., January 30, 1855; interment in the Knickerbocker family cemetery, Schaghticoke, Rensselaer County, N.Y.", "relationship" : [], "jobPositions" : [{ "job" : { "name" : "Representative", "jobType" : "CongressMemberJob" }, "startDate" : "1809-05-22", "startCirca" : false, "congressAffiliation" : { "congress" : { "name" : "The 11th United States Congress", "congressNumber" : 11, "congressType" : "USCongress", "startDate" : "1809-03-04", "endDate" : "1811-03-03" }, "partyAffiliation" : [{ "party" : { "name" : "Federalist" } }], "caucusAffiliation" : [{ "party" : { "name" : "Federalist" } }], "represents" : { "regionType" : "DistrictRegion", "regionCode" : "NY" }, "note" : [{ "type" : "Note", "noteType" : "FootNote", "content" : "One of two elected to represent 6th district." }] } }], "creativeWork" : [], "researchRecord" : [] }
