{ "usCongressBioId" : "W000506", "familyName" : "Williams", "givenName" : "James", "unaccentedFamilyName" : "Williams", "unaccentedGivenName" : "James", "birthDate" : "1825", "birthCirca" : false, "deathDate" : "1899", "deathCirca" : false, "profileText" : "A Representative from Delaware; born in Philadelphia, Pa., August 4, 1825; completed preparatory studies; moved to Kenton, Kent County, Del., in 1844 and engaged in agricultural pursuits; member of the State house of representatives in 1856 and 1862; served in the State senate in 1866 and 1871; delegate to the Democratic National Convention in 1872; elected as a Democrat to the Forty-fourth and Forty-fifth Congresses (March 4, 1875-March 3, 1879); was not a candidate for renomination in 1878; resumed agricultural pursuits; moved to Smyrna, Del., in 1891 and continued farming until his death on April 12, 1899; interment in St. Peter's Cemetery.", "relationship" : [], "jobPositions" : [{ "job" : { "name" : "Representative", "jobType" : "CongressMemberJob" }, "congressAffiliation" : { "congress" : { "name" : "The 44th United States Congress", "congressNumber" : 44, "congressType" : "USCongress", "startDate" : "1875-03-05", "endDate" : "1877-03-04" }, "partyAffiliation" : [{ "party" : { "name" : "Democrat" } }], "caucusAffiliation" : [{ "party" : { "name" : "Democrat" } }], "represents" : { "regionType" : "DistrictRegion", "regionCode" : "DE" } } }, { "job" : { "name" : "Representative", "jobType" : "CongressMemberJob" }, "congressAffiliation" : { "congress" : { "name" : "The 45th United States Congress", "congressNumber" : 45, "congressType" : "USCongress", "startDate" : "1877-03-05", "endDate" : "1879-03-03" }, "partyAffiliation" : [{ "party" : { "name" : "Democrat" } }], "caucusAffiliation" : [{ "party" : { "name" : "Democrat" } }], "represents" : { "regionType" : "DistrictRegion", "regionCode" : "DE" } } }], "creativeWork" : [], "researchRecord" : [] }
